MANIFEST.in
README.rst
setup.py
docs/HISTORY.txt
docs/LICENSE.GPL
docs/LICENSE.txt
ftw/__init__.py
ftw.autofeature.egg-info/PKG-INFO
ftw.autofeature.egg-info/SOURCES.txt
ftw.autofeature.egg-info/dependency_links.txt
ftw.autofeature.egg-info/entry_points.txt
ftw.autofeature.egg-info/namespace_packages.txt
ftw.autofeature.egg-info/not-zip-safe
ftw.autofeature.egg-info/requires.txt
ftw.autofeature.egg-info/top_level.txt
ftw/autofeature/__init__.py
ftw/autofeature/dump.py
ftw/autofeature/extras.py
ftw/autofeature/meta.zcml
ftw/autofeature/utils.py
ftw/autofeature/tests/__init__.py
ftw/autofeature/tests/helpers.py
ftw/autofeature/tests/test_dump.py
ftw/autofeature/tests/test_extras.py
ftw/autofeature/tests/test_utils.py