Metadata-Version: 1.1
Name: ftw.autofeature
Version: 1.0.0
Summary: ftw.autofeature automatically registers ZCML features.
Home-page: https://github.com/4teamwork/ftw.autofeature
Author: 4teamwork AG
Author-email: mailto:info@4teamwork.ch
License: GPL2
Keywords: ftw autofeature zcml feature
Platform: UNKNOWN
Classifier: Environment :: Web Environment
Classifier: Framework :: Plone
Classifier: Framework :: Plone :: 4.3
Classifier: Intended Audience :: Developers
Classifier: License :: OSI Approved :: GNU General Public License (GPL)
Classifier: Programming Language :: Python
Classifier: Topic :: Software Development :: Libraries :: Python Modules
